<?xml version="1.0" encoding="utf-8"?>
	<annotation>
		<folder></folder>
		<filename>20200727104213_92116405.jpg</filename>
		<source>
			<database>Unknown</database>
		</source>
		<path>20200727104213_92116405.jpg</path>
		<size>
			<width>1920</width>
			<height>1080</height>
			<depth>3</depth>
		</size>
		<object>
			<name>Car</name>
			<pose>Unspecified</pose>
			<truncated>0</truncated>
			<difficult>0</difficult>
			<bndbox>
				<xmin>189</xmin>
				<ymin>34</ymin>
				<xmax>1835</xmax>
				<ymax>907</ymax>
			</bndbox>
		</object>
		<object>
			<name>License Plate</name>
			<pose>Unspecified</pose>
			<truncated>0</truncated>
			<difficult>0</difficult>
			<bndbox>
				<xmin>1141</xmin>
				<ymin>483</ymin>
				<xmax>1578</xmax>
				<ymax>637</ymax>
			</bndbox>
		</object>
	</annotation>
