<?xml version="1.0" encoding="utf-8"?>
	<annotation>
		<folder></folder>
		<filename>20200727104731_0474505777.jpg</filename>
		<source>
			<database>Unknown</database>
		</source>
		<path>20200727104731_0474505777.jpg</path>
		<size>
			<width>1920</width>
			<height>1080</height>
			<depth>3</depth>
		</size>
		<object>
			<name>Car</name>
			<pose>Unspecified</pose>
			<truncated>0</truncated>
			<difficult>0</difficult>
			<bndbox>
				<xmin>61</xmin>
				<ymin>20</ymin>
				<xmax>1338</xmax>
				<ymax>738</ymax>
			</bndbox>
		</object>
		<object>
			<name>License Plate</name>
			<pose>Unspecified</pose>
			<truncated>0</truncated>
			<difficult>0</difficult>
			<bndbox>
				<xmin>781</xmin>
				<ymin>377</ymin>
				<xmax>1038</xmax>
				<ymax>516</ymax>
			</bndbox>
		</object>
	</annotation>
