<?xml version="1.0" encoding="utf-8"?>
	<annotation>
		<folder></folder>
		<filename>20200823175732_0623560857.jpg</filename>
		<source>
			<database>Unknown</database>
		</source>
		<path>20200823175732_0623560857.jpg</path>
		<size>
			<width>1280</width>
			<height>720</height>
			<depth>3</depth>
		</size>
		<object>
			<name>Car</name>
			<pose>Unspecified</pose>
			<truncated>0</truncated>
			<difficult>0</difficult>
			<bndbox>
				<xmin>52</xmin>
				<ymin>7</ymin>
				<xmax>1121</xmax>
				<ymax>624</ymax>
			</bndbox>
		</object>
		<object>
			<name>License Plate</name>
			<pose>Unspecified</pose>
			<truncated>0</truncated>
			<difficult>0</difficult>
			<bndbox>
				<xmin>692</xmin>
				<ymin>335</ymin>
				<xmax>972</xmax>
				<ymax>444</ymax>
			</bndbox>
		</object>
	</annotation>
